setup.py
Apache_ShenYu_Client.egg-info/PKG-INFO
Apache_ShenYu_Client.egg-info/SOURCES.txt
Apache_ShenYu_Client.egg-info/dependency_links.txt
Apache_ShenYu_Client.egg-info/entry_points.txt
Apache_ShenYu_Client.egg-info/requires.txt
Apache_ShenYu_Client.egg-info/top_level.txt
apache_shenyu_client/__init__.py
apache_shenyu_client/api.py
apache_shenyu_client/config.py
apache_shenyu_client/exception.py
apache_shenyu_client/main.py
apache_shenyu_client/register.py